{
    "files": [
        {
            "type": "radioButton",
            "layoutDefinition": {
                "rows": 1,
                "cols": 6,
                "offset": 2
            },
            "style": {
                "component": "class-a"
            },
            "position": {
                "index": 0,
                "order": 0,
                "col": 2
            },
            "getOptionList": [
                "getRadioList"
            ],
            "visibilty": "required",
            "bindData": "option",
            "action": [
                {
                    "type": "change",
                    "actionName": "changeRadio"
                }
            ]
        },
        {
            "type": "checkbox",
            "bindData": "checkbox",
            "style": {
                "component": "class-a"
            },
            "getOptionList": [
                "getcheckboxList"
            ],
            "layoutDefinition": {
                "rows": 1,
                "cols": 12

            },
            "position": {
                "index": 0,
                "order": 1,
                "col": 2
            },
            "visibilty": "required"
        },
        {
            "type": "checkbox",
            "bindData": "checkbox",
            "style": {
                "component": "class-a"
            },
            "getOptionList": [
                "getcheckboxList"
            ],
            "layoutDefinition": {
                "rows": 1,
                "cols": 12

            },
            "position": {
                "index": 1,
                "order": 1,
                "col": 2
            },
            "visibilty": "required"
        }
    ],
    "action":[
        {
            "type": "load",
            "actionName": "loadData"
        }
    ]
}